MANIFEST.in
README.rst
setup.py
scripts/vesna_log
scripts/vesna_rftest
scripts/vesna_rftest_plot
test/__init__.py
test/test_spectrumsensor.py
vesna/rftest/__init__.py
vesna/spectrumsensor/__init__.py
vesna_spectrumsensor.egg-info/PKG-INFO
vesna_spectrumsensor.egg-info/SOURCES.txt
vesna_spectrumsensor.egg-info/dependency_links.txt
vesna_spectrumsensor.egg-info/namespace_packages.txt
vesna_spectrumsensor.egg-info/requires.txt
vesna_spectrumsensor.egg-info/top_level.txt