Metadata-Version: 1.0
Name: vesna-spectrumsensor
Version: 1.0.7
Summary: Tools for talking to the VESNA spectrum sensor applicaiton
Home-page: https://github.com/avian2/vesna-spectrum-sensor
Author: Tomaz Solc
Author-email: tomaz.solc@ijs.si
License: GPL
Platform: UNKNOWN
